{
  "schema_version": 2,
  "run_id": "fixture-v2-per-instance",
  "started_at": "2026-04-20T09:00:00Z",
  "updated_at": "2026-04-20T09:20:00Z",
  "ended_at": "2026-04-20T09:21:10Z",
  "character": "KIN",
  "ascension": 4,
  "floor_reached": 15,
  "outcome": "win",
  "game_start_time": 1713603600,
  "aggregates": {
    "CARD.STRIKE_KIN#1": {
      "plays": 3,
      "total_intended": 18,
      "total_blocked": 2,
      "total_overkill": 0,
      "total_effective": 16,
      "kills": 1,
      "total_energy_spent": 3,
      "total_energy_generated": 0,
      "total_block_gained": 0,
      "times_drawn": 4,
      "times_discarded": 1,
      "times_placed_on_top_from_hand": 0,
      "times_placed_on_top_from_discard": 0,
      "times_exhausted_other_cards": 0,
      "total_hp_lost": 0,
      "times_cards_drawn": 0,
      "floor_added": 1,
      "initial_upgrade_level": 0,
      "removed": false
    },
    "CARD.ENERGY_SURGE#1": {
      "plays": 1,
      "total_intended": 0,
      "total_blocked": 0,
      "total_overkill": 0,
      "total_effective": 0,
      "kills": 0,
      "total_energy_spent": 0,
      "total_energy_generated": 2,
      "total_block_gained": 0,
      "times_drawn": 1,
      "times_discarded": 0,
      "times_placed_on_top_from_hand": 0,
      "times_placed_on_top_from_discard": 0,
      "times_exhausted_other_cards": 0,
      "total_hp_lost": 0,
      "times_cards_drawn": 0,
      "floor_added": 5,
      "initial_upgrade_level": 1,
      "removed": false
    }
  },
  "events": [
    {
      "t": "2026-04-20T09:02:00Z",
      "type": "card_played",
      "card_id": "CARD.STRIKE_KIN#1",
      "target": "KIN_PRIEST_0",
      "energy_spent": 1,
      "floor": 5
    },
    {
      "t": "2026-04-20T09:02:00Z",
      "type": "damage_received",
      "card_id": "CARD.STRIKE_KIN#1",
      "receiver": "KIN_PRIEST_0",
      "blocked": 0,
      "unblocked": 6,
      "overkill": 0,
      "killed": false
    },
    {
      "t": "2026-04-20T09:10:00Z",
      "type": "card_upgraded",
      "card_id": "CARD.ENERGY_SURGE#1",
      "floor": 7,
      "upgrade_level": 1
    },
    {
      "t": "2026-04-20T09:12:00Z",
      "type": "card_played",
      "card_id": "CARD.ENERGY_SURGE#1",
      "energy_spent": 0,
      "energy_gained": 2,
      "floor": 8
    }
  ],
  "instance_numbers_by_def": {
    "CARD.STRIKE_KIN": [
      1
    ],
    "CARD.ENERGY_SURGE": [
      1
    ]
  },
  "def_counters": {
    "CARD.STRIKE_KIN": 1,
    "CARD.ENERGY_SURGE": 1
  }
}
